agwr/__init__.py
agwr/vgwr.py
agwr-2.0.0.dist-info/licenses/LICENSE
agwr-2.0.0.dist-info/METADATA
agwr-2.0.0.dist-info/WHEEL
agwr-2.0.0.dist-info/top_level.txt
agwr-2.0.0.dist-info/RECORD
