Metadata-Version: 2.4
Name: agwr
Version: 2.0.0
Summary: 各向异性地理加权回归模型实现 (VGWR)
Home-page: https://github.com/agwr-team/agwr
Author: AGWR开发团队
Author-email: AGWR开发团队 <agwr@example.com>
Maintainer-email: AGWR开发团队 <agwr@example.com>
License: MIT
Project-URL: Homepage, https://github.com/agwr-team/agwr
Project-URL: Documentation, https://agwr.readthedocs.io/
Project-URL: Repository, https://github.com/agwr-team/agwr
Project-URL: Bug Tracker, https://github.com/agwr-team/agwr/issues
Keywords: geographically weighted regression,spatial statistics,anisotropy,gwr,vgwr,agwr
Classifier: Development Status :: 4 - Beta
Classifier: Intended Audience :: Science/Research
Classifier: License :: OSI Approved :: MIT License
Classifier: Operating System :: OS Independent
Classifier: Programming Language :: Python :: 3
Classifier: Programming Language :: Python :: 3.8
Classifier: Programming Language :: Python :: 3.9
Classifier: Programming Language :: Python :: 3.10
Classifier: Programming Language :: Python :: 3.11
Classifier: Programming Language :: Python :: 3.12
Classifier: Topic :: Scientific/Engineering :: Information Analysis
Classifier: Topic :: Scientific/Engineering :: Mathematics
Requires-Python: >=3.8
License-File: LICENSE
Requires-Dist: numpy>=1.20.0
Requires-Dist: pandas>=1.3.0
Requires-Dist: scipy>=1.7.0
Provides-Extra: dev
Requires-Dist: pytest>=6.0; extra == "dev"
Requires-Dist: pytest-cov>=2.0; extra == "dev"
Requires-Dist: black>=21.0; extra == "dev"
Requires-Dist: flake8>=3.8; extra == "dev"
Provides-Extra: docs
Requires-Dist: sphinx>=4.0; extra == "docs"
Requires-Dist: sphinx-rtd-theme>=1.0; extra == "docs"
Dynamic: author
Dynamic: home-page
Dynamic: license-file
Dynamic: requires-python
